psynlig/__init__.py
psynlig/colors.py
psynlig/common.py
psynlig/heatmap.py
psynlig/histogram.py
psynlig/scatter.py
psynlig/version.py
psynlig/pca/__init__.py
psynlig/pca/loadings.py
psynlig/pca/scores.py
psynlig/pca/variance.py
psynlig-0.2.2.dev0.dist-info/LICENSE
psynlig-0.2.2.dev0.dist-info/METADATA
psynlig-0.2.2.dev0.dist-info/WHEEL
psynlig-0.2.2.dev0.dist-info/top_level.txt
psynlig-0.2.2.dev0.dist-info/RECORD
