Metadata-Version: 2.1
Name: psynlig
Version: 0.2.2.dev0
Summary: A package for creating plots with matplotlib.
Home-page: https://github.com/andersle/psynlig
Author: Anders Lervik
Author-email: andersle@gmail.com
License: MIT
Keywords: matplotlib
Platform: UNKNOWN
Classifier: Development Status :: 3 - Alpha
Classifier: Environment :: Console
Classifier: Intended Audience :: End Users/Desktop
Classifier: License :: OSI Approved :: MIT License
Classifier: Natural Language :: English
Classifier: Operating System :: MacOS :: MacOS X
Classifier: Operating System :: POSIX
Classifier: Programming Language :: Python :: 3
Classifier: Programming Language :: Python :: 3.8
Classifier: Programming Language :: Python :: 3.9
Classifier: Topic :: Other/Nonlisted Topic
License-File: LICENSE
Requires-Dist: adjustText
Requires-Dist: jupyter
Requires-Dist: matplotlib
Requires-Dist: numpy
Requires-Dist: pandas
Requires-Dist: scikit-learn
Requires-Dist: scipy
Requires-Dist: shapely
Requires-Dist: sphinx
Requires-Dist: sphinx-gallery
Requires-Dist: sphinx-rtd-theme
Requires-Dist: tabulate
